markdown_mermaid.py
markdown_mermaid-0.2.dist-info/LICENSE
markdown_mermaid-0.2.dist-info/METADATA
markdown_mermaid-0.2.dist-info/WHEEL
markdown_mermaid-0.2.dist-info/top_level.txt
markdown_mermaid-0.2.dist-info/RECORD
